oneshot/__init__.py
oneshot/analyzeimage.py
oneshot/Beamlines.py
oneshot/E200_cam_E_cal.py
oneshot/findpinch.py
oneshot/fitBeamlineScan.py
oneshot/fitbowtie.py
oneshot/fitimage.py
oneshot/getstd.py
oneshot/histcher.py
oneshot/histenergy.py
oneshot/plotfit.py
oneshot/tradquadscan.py
OneShot-0.2.0.dist-info/DESCRIPTION.rst
OneShot-0.2.0.dist-info/METADATA
OneShot-0.2.0.dist-info/metadata.json
OneShot-0.2.0.dist-info/RECORD
OneShot-0.2.0.dist-info/top_level.txt
OneShot-0.2.0.dist-info/WHEEL
